[

{
    "locationId": "H1",
    "name": "JTI at Gloucester Road eastbound near the Revenue Tower",
    "latitude": 22.279311622,
    "longitude": 114.172101664,
    "userComments": []
},
{
   "locationId": "H2",
    "name": "JTI at Canal Road Flyover northbound near exit of Aberdeen Tunnel",
    "latitude": 22.271587756,
    "longitude": 114.180185283,
    "userComments": [] 
},
{
    "locationId": "H3",
    "name": "JTI at Island Eastern Corridor westbound near City Garden",
    "latitude": 22.292018819,
    "longitude": 114.193869616,
    "userComments": []
},
{
    "locationId": "H11",
    "name": "JTI at Island Eastern Corridor westbound near Lei King Wan",
    "latitude": 22.285235888,
    "longitude": 114.221346549,
    "userComments": []
},
{
    "locationId": "K01",
    "name": "JTI at Ferry Street southbound near Charming Garden",
    "latitude": 22.315044916,
    "longitude": 114.166786346,
    "userComments": []
},
{
    "locationId": "K02",
    "name": "JTI at Gascoigne Road eastbound near the Hong Kong Polytechnic University",
    "latitude": 22.305896494,
    "longitude": 114.178474746,
    "userComments": []
},
{
   "locationId": "K03",
    "name": "JTI at Waterloo Road southbound near Kowloon Hospital",
    "latitude": 22.324182195,
    "longitude": 114.178378266,
    "userComments": []
},
{
    "locationId": "K04",
    "name": "JTI at Princess Margaret Road southbound near Oi Man Estate",
    "latitude": 22.313310630,
    "longitude": 114.176931903,
    "userComments": []
},
{
    "locationId": "K05",
    "name": "JTI at Kai Fuk Road northbound near the petrol stations",
    "latitude": 22.319902728,
    "longitude": 114.206732056,
    "userComments": []
},
{
    "locationId": "K06",
    "name": "JTI at Chatham Road North southbound near Fat Kwong Street Playground",
    "latitude": 22.309177485,
    "longitude": 114.184084134,
    "userComments": []
},
{
    "locationId": "SJ1",
    "name": "JTI at Tai Po Road – Sha Tin near the Racecourse",
    "latitude": 22.404797024,
    "longitude": 114.207347960,
    "userComments": []
},
{
    "locationId": "SJ2",
    "name": "JTI at Tate’s Cairn Highway near Shek Mun" ,
    "latitude": 22.389757785,
    "longitude": 114.210593926,
    "userComments": []
},
{
    "locationId": "SJ3",
    "name": "JTI at Tolo Highway near Science Park" ,
    "latitude": 22.426975789,
    "longitude": 114.206972621,
    "userComments": []
},
{
    "locationId": "SJ4",
    "name": "JTI at San Tin Highway near Pok Wai Road" ,
    "latitude": 22.464106829,
    "longitude": 114.053710459,
    "userComments": []
},
{
    "locationId": "SJ5",
    "name": "JTI at Tuen Mun Road near Tuen Mun Heung Sze Wui Road",
    "latitude": 22.401075772,
    "longitude": 113.977226590,
    "userComments": []
}
]
